octodns_porkbun/__init__.py
octodns_porkbun/py.typed
octodns_porkbun-0.1.0.dist-info/WHEEL
octodns_porkbun-0.1.0.dist-info/METADATA
octodns_porkbun-0.1.0.dist-info/RECORD
