Metadata-Version: 2.4
Name: octodns-porkbun
Version: 0.1.0
Summary: Porkbun DNS provider for octoDNS
Keywords: dns,porkbun,octodns,infrastructure
Author: Major Hayden
Author-email: Major Hayden <major@mhtx.net>
License-Expression: MIT
Classifier: Development Status :: 4 - Beta
Classifier: Intended Audience :: Developers
Classifier: Intended Audience :: System Administrators
Classifier: License :: OSI Approved :: MIT License
Classifier: Programming Language :: Python :: 3.13
Classifier: Programming Language :: Python :: 3.14
Classifier: Topic :: Internet :: Name Service (DNS)
Classifier: Typing :: Typed
Requires-Dist: octodns>=1.5.0
Requires-Dist: oinker>=0.1.0
Requires-Python: >=3.13
Project-URL: Homepage, https://github.com/major/octodns-porkbun
Project-URL: Repository, https://github.com/major/octodns-porkbun
